MANIFEST.in
README.rst
VERSION
setup.py
hitchdoc/__init__.py
hitchdoc/database.py
hitchdoc/documentation.py
hitchdoc/exceptions.py
hitchdoc/hitchstory.py
hitchdoc/recorder.py
hitchdoc.egg-info/PKG-INFO
hitchdoc.egg-info/SOURCES.txt
hitchdoc.egg-info/dependency_links.txt
hitchdoc.egg-info/not-zip-safe
hitchdoc.egg-info/requires.txt
hitchdoc.egg-info/top_level.txt
hitchdoc/templates/default.jinja2